LICENSE
MANIFEST.in
README.rst
VERSION
setup.cfg
setup.py
django_migration_fixture/__init__.py
django_migration_fixture.egg-info/PKG-INFO
django_migration_fixture.egg-info/SOURCES.txt
django_migration_fixture.egg-info/dependency_links.txt
django_migration_fixture.egg-info/not-zip-safe
django_migration_fixture.egg-info/requires.txt
django_migration_fixture.egg-info/top_level.txt
django_migration_fixture/management/__init__.py
django_migration_fixture/management/commands/__init__.py
django_migration_fixture/management/commands/create_initial_data_fixtures.py
requirements/default.txt
requirements/pkgutils.txt
requirements/test.txt
requirements/test3.txt